django_ariadne_jwt/__init__.py
django_ariadne_jwt/backends.py
django_ariadne_jwt/decorators.py
django_ariadne_jwt/exceptions.py
django_ariadne_jwt/middleware.py
django_ariadne_jwt/resolvers.py
django_ariadne_jwt/types.py
django_ariadne_jwt/utils.py
django_ariadne_jwt-0.2.0.dist-info/AUTHORS.rst
django_ariadne_jwt-0.2.0.dist-info/LICENSE
django_ariadne_jwt-0.2.0.dist-info/METADATA
django_ariadne_jwt-0.2.0.dist-info/WHEEL
django_ariadne_jwt-0.2.0.dist-info/top_level.txt
django_ariadne_jwt-0.2.0.dist-info/RECORD
